mlpack/fastmks.cpython-37m-x86_64-linux-gnu.so
mlpack/radical.cpython-37m-x86_64-linux-gnu.so
mlpack/bayesian_linear_regression.cpython-37m-x86_64-linux-gnu.so
mlpack/hmm_viterbi.cpython-37m-x86_64-linux-gnu.so
mlpack/perceptron.cpython-37m-x86_64-linux-gnu.so
mlpack/emst.cpython-37m-x86_64-linux-gnu.so
mlpack/local_coordinate_coding.cpython-37m-x86_64-linux-gnu.so
mlpack/gmm_generate.cpython-37m-x86_64-linux-gnu.so
mlpack/dbscan.cpython-37m-x86_64-linux-gnu.so
mlpack/kernel_pca.cpython-37m-x86_64-linux-gnu.so
mlpack/mean_shift.cpython-37m-x86_64-linux-gnu.so
mlpack/lars.cpython-37m-x86_64-linux-gnu.so
mlpack/lmnn.cpython-37m-x86_64-linux-gnu.so
mlpack/preprocess_one_hot_encoding.cpython-37m-x86_64-linux-gnu.so
mlpack/preprocess_binarize.cpython-37m-x86_64-linux-gnu.so
mlpack/nbc.cpython-37m-x86_64-linux-gnu.so
mlpack/logistic_regression.cpython-37m-x86_64-linux-gnu.so
mlpack/kmeans.cpython-37m-x86_64-linux-gnu.so
mlpack/matrix_utils.py
mlpack/cf.cpython-37m-x86_64-linux-gnu.so
mlpack/linear_regression.cpython-37m-x86_64-linux-gnu.so
mlpack/preprocess_split.cpython-37m-x86_64-linux-gnu.so
mlpack/krann.cpython-37m-x86_64-linux-gnu.so
mlpack/adaboost.cpython-37m-x86_64-linux-gnu.so
mlpack/hoeffding_tree.cpython-37m-x86_64-linux-gnu.so
mlpack/gmm_probability.cpython-37m-x86_64-linux-gnu.so
mlpack/linear_svm.cpython-37m-x86_64-linux-gnu.so
mlpack/decision_stump.cpython-37m-x86_64-linux-gnu.so
mlpack/softmax_regression.cpython-37m-x86_64-linux-gnu.so
mlpack/kfn.cpython-37m-x86_64-linux-gnu.so
mlpack/preprocess_describe.cpython-37m-x86_64-linux-gnu.so
mlpack/hmm_generate.cpython-37m-x86_64-linux-gnu.so
mlpack/decision_tree.cpython-37m-x86_64-linux-gnu.so
mlpack/hmm_train.cpython-37m-x86_64-linux-gnu.so
mlpack/gmm_train.cpython-37m-x86_64-linux-gnu.so
mlpack/approx_kfn.cpython-37m-x86_64-linux-gnu.so
mlpack/preprocess_scale.cpython-37m-x86_64-linux-gnu.so
mlpack/nmf.cpython-37m-x86_64-linux-gnu.so
mlpack3-3.4.2.dist-info/top_level.txt
mlpack3-3.4.2.dist-info/RECORD
mlpack3-3.4.2.dist-info/METADATA
mlpack3-3.4.2.dist-info/WHEEL
