Metadata-Version: 2.1
Name: mlpack3
Version: 3.4.2
Summary: a flexible, fast machine learning library
Home-page: http://www.mlpack.org/
Author: mlpack developers
Author-email: mlpack@lists.mlpack.org
License: BSD
Project-URL: Documentation, http://www.mlpack.org/docs/mlpack-3.4.2/python.html
Project-URL: Source, https://github.com/mlpack/mlpack/
Project-URL: Tracker, https://github.com/mlpack/mlpack/issues
Keywords: machine learning,data mining,deep learning,optimization
Platform: UNKNOWN
Classifier: Development Status :: 5 - Production/Stable
Classifier: Intended Audience :: Science/Research
Classifier: License :: OSI Approved :: BSD License
Classifier: Topic :: Scientific/Engineering :: Artificial Intelligence
Classifier: Topic :: Scientific/Engineering :: Mathematics
Classifier: Topic :: Software Development :: Libraries
Classifier: Topic :: Software Development :: Libraries :: Application Frameworks
Requires-Dist: cython (>=0.24)
Requires-Dist: numpy
Requires-Dist: pandas
